eureka_template/__init__.py
eureka_template/application.py
eureka_template/command.py
eureka_template/template.py
eureka_template/template_writer.py
eureka_template-0.0.4.data/scripts/eureka-template
eureka_template-0.0.4.dist-info/DESCRIPTION.rst
eureka_template-0.0.4.dist-info/METADATA
eureka_template-0.0.4.dist-info/metadata.json
eureka_template-0.0.4.dist-info/RECORD
eureka_template-0.0.4.dist-info/top_level.txt
eureka_template-0.0.4.dist-info/WHEEL
underaid/__init__.py
underaid/ansible_utils/__init__.py
underaid/boto_utils/__init__.py
underaid/boto_utils/connection.py
underaid/boto_utils/exceptions.py
