Metadata-Version: 2.0
Name: eureka-template
Version: 0.0.4
Summary: Eureka Templating Library
Home-page: UNKNOWN
Author: Jorge Dias
Author-email: jorge@mrdias.com
License: UNKNOWN
Platform: UNKNOWN
Requires-Dist: eureka-client (>=0.6.2)
Requires-Dist: jinja2
